pdfgenius/__init__.py
pdfgenius/cli.py
pdfgenius/key_manager.py
pdfgenius/utils.py
pdfgenius/extractors/__init__.py
pdfgenius/extractors/base.py
pdfgenius/extractors/gemini_extractor.py
pdfgenius/extractors/openai_extractor.py
pdfgenius-0.1.3.dist-info/METADATA
pdfgenius-0.1.3.dist-info/WHEEL
pdfgenius-0.1.3.dist-info/entry_points.txt
pdfgenius-0.1.3.dist-info/top_level.txt
pdfgenius-0.1.3.dist-info/RECORD
