Metadata-Version: 2.2
Name: pdfgenius
Version: 0.1.3
Requires-Python: >=3.7
Requires-Dist: pdf2image
Requires-Dist: Pillow
Requires-Dist: python-dotenv
Requires-Dist: click
Requires-Dist: google-genai
Requires-Dist: openai
Requires-Dist: cryptography
Dynamic: description
Dynamic: description-content-type
Dynamic: requires-dist
Dynamic: requires-python
